UniversalWebScraping
