Metadata-Version: 1.0
Name: UniversalWebScraping
Version: 0.1.8
Summary: universal web scraping
Home-page: http://lazcode.com
Author: Zulu Ng
Author-email: ngz1357@gmail.com
License: mit
Keywords: scraping
Platform: UNKNOWN
